symcollab/theories/__init__.py
symcollab/theories/boolean.py
symcollab/theories/fields.py
symcollab/theories/groups.py
symcollab/theories/inductive.py
symcollab/theories/lemma.py
symcollab/theories/listing.py
symcollab/theories/nat.py
symcollab/theories/optional.py
symcollab/theories/pair.py
symcollab/theories/rings.py
symcollab/theories/old/_boolean_rings_old.py
symcollab/theories/old/_fields_old.py
symcollab/theories/old/_groups_old.py
symcollab/theories/old/_rings_old.py
symcollab_theories-0.1.1.dist-info/METADATA
symcollab_theories-0.1.1.dist-info/WHEEL
symcollab_theories-0.1.1.dist-info/top_level.txt
symcollab_theories-0.1.1.dist-info/RECORD
